Metadata-Version: 2.1
Name: py-cobra
Version: 0.1.0
Summary: A fast, flexible and simple development environment framework for Ethereum smart contract, testing and deployment on Ethereum virtual machine(EVM). https://cobraframework.github.io
Home-page: https://github.com/cobraframework/cobra
Author: Meheret Tesfaye
Author-email: meherett@zoho.com
License: MIT
Keywords: cobra
Platform: UNKNOWN
Classifier: Development Status :: 3 - Alpha
Classifier: Intended Audience :: Developers
Classifier: Topic :: Software Development :: Build Tools
Classifier: License :: OSI Approved :: MIT License
Classifier: Programming Language :: Python :: 3
Classifier: Programming Language :: Python :: 3.6
Classifier: Programming Language :: Python :: 3.7
Requires-Python: >=3.6,<4
Requires-Dist: colorama (==0.4.1)
Requires-Dist: websockets (==6.0)
Requires-Dist: cryptography (==2.5)
Requires-Dist: cobra-hdwallet (==0.3.1)
Requires-Dist: eth-abi (==1.2.2)
Requires-Dist: eth-keyfile (==0.5.1)
Requires-Dist: eth-tester (==0.1.0b33)
Requires-Dist: eth-typing (==1.3.0)
Requires-Dist: eth-utils (==1.4.1)
Requires-Dist: py-evm (==0.2.0a33)
Requires-Dist: py-solc (==3.2.0)
Requires-Dist: pycryptodome (==3.7.3)
Requires-Dist: pysha3 (==1.0.2)
Requires-Dist: pytest (==3.10.1)
Requires-Dist: pytest-console-scripts (==0.1.9)
Requires-Dist: pytest-cobra (==1.0.1)
Requires-Dist: PyYAML (==3.13)
Requires-Dist: pytest-cov (==2.7.1)
Requires-Dist: requests (==2.21.0)
